logfmt/__init__.py
logfmt_julian_sobott-0.4.1.dist-info/WHEEL
logfmt_julian_sobott-0.4.1.dist-info/METADATA
logfmt_julian_sobott-0.4.1.dist-info/RECORD
